{"assets/images/bg.png":["assets/images/bg.png"],"assets/images/circle.png":["assets/images/circle.png"],"assets/images/img.png":["assets/images/img.png"],"assets/images/img2.png":["assets/images/img2.png"],"assets/svg/akun.svg":["assets/svg/akun.svg"],"assets/svg/arrow_down.svg":["assets/svg/arrow_down.svg"],"assets/svg/camera.svg":["assets/svg/camera.svg"],"assets/svg/chat.svg":["assets/svg/chat.svg"],"assets/svg/home.svg":["assets/svg/home.svg"],"assets/svg/pin.svg":["assets/svg/pin.svg"],"assets/svg/search.svg":["assets/svg/search.svg"],"assets/svg/star.svg":["assets/svg/star.svg"],"packages/cupertino_icons/assets/CupertinoIcons.ttf":["packages/cupertino_icons/assets/CupertinoIcons.ttf"]}